send_to_log_center_ys/__init__.py
send_to_log_center_ys/send_log.py
send_log_ys-0.0.2.dist-info/LICENSE
send_log_ys-0.0.2.dist-info/METADATA
send_log_ys-0.0.2.dist-info/WHEEL
send_log_ys-0.0.2.dist-info/top_level.txt
send_log_ys-0.0.2.dist-info/RECORD
