Metadata-Version: 2.1
Name: send-log-ys
Version: 0.0.2
Summary: send log to log_center for ys
Home-page: https://github.com/wikensmith/send_to_log_center_ys.git
Author: wiken
Author-email: wiken01@qq.com
License: MIT
Platform: UNKNOWN
Classifier: Programming Language :: Python :: 3
Requires-Dist: requests (==2.24.0)
